{
  "id": "2020-05-03_small_mercies",
  "title": "Small Mercies",
  "type": "poem",
  "date": "2020-05-03",
  "tags": [
    "pandemic",
    "stillness",
    "gratitude",
    "spring",
    "isolation"
  ],
  "content": "The neighbor's cat has been sleeping\nin the planter box all week —\na gray parenthesis\ncurled around the not-yet-blooming.\n\nI watch her from the window.\nShe does not know about any of this.\n\nThe bread I baked yesterday\nwas ugly and dense\nand I ate it warm with butter\nstanding over the sink\nand it was the best thing\nthat had happened to me in weeks.\n\nA mercy: the way light moves\nacross a room in the morning.\n\nA mercy: the sound of birds\nwho also did not get the news.\n\nI am learning to receive\nthe small things\nwithout apology —\nto let the warmth of bread\nand the indifferent grace of cats\nbe enough,\n\nat least\nfor today."
}